DoerGPIO/GPIO.py
DoerGPIO/__init__.py
DoerGPIO/adaptors.py
DoerGPIO/doerserial.py
DoerGPIO/ports_unix.py
DoerGPIO/ports_win32.py
DoerGPIO/portscan.py
DoerGPIO/protocol.py
doergpio-0.4.dist-info/METADATA
doergpio-0.4.dist-info/WHEEL
doergpio-0.4.dist-info/top_level.txt
doergpio-0.4.dist-info/RECORD
