Metadata-Version: 2.4
Name: DoerGPIO
Version: 0.4
Summary: USB GPIO interface for Python
Home-page: 
Author: Pasco Tang
Author-email: jacobhere@gmail.com
Classifier: Development Status :: 4 - Beta
Classifier: Intended Audience :: Developers
Classifier: Programming Language :: Python :: 3
Classifier: Programming Language :: Python :: 3.9
Requires-Python: >=3.9
Requires-Dist: pyserial
Dynamic: author
Dynamic: author-email
Dynamic: classifier
Dynamic: description
Dynamic: description-content-type
Dynamic: requires-dist
Dynamic: requires-python
Dynamic: summary
